chess_server/__init__.py
chess_server/server.py
chess_server-0.1.0.dist-info/WHEEL
chess_server-0.1.0.dist-info/METADATA
chess_server-0.1.0.dist-info/RECORD
