Metadata-Version: 2.1
Name: chess-server
Version: 0.1.0
Summary: 
Author: Tilak Patel
Author-email: ptilak142@gmail.com
Requires-Python: >=3.10,<4.0
Classifier: Programming Language :: Python :: 3
Classifier: Programming Language :: Python :: 3.10
Requires-Dist: asyncio (>=3.4.3,<4.0.0)
Requires-Dist: chess (>=1.9.0,<2.0.0)
Requires-Dist: websockets (>=10.3,<11.0)
